{
    "id": 603692,
    "results": {
      "US": {
        "link": "https://www.themoviedb.org/movie/603692-john-wick-chapter-4/watch?locale=US",
        "flatrate": [
          {
            "logo_path": "/hB24bAA8Y2ei6pbEGuCNdKUOjxI.jpg",
            "provider_id": 1855,
            "provider_name": "Starz Apple TV Channel",
            "display_priority": 21
          },
          {
            "logo_path": "/5OAb2w7D9C2VHa0k5PaoAYeFYFE.jpg",
            "provider_id": 634,
            "provider_name": "Starz Roku Premium Channel",
            "display_priority": 32
          },
          {
            "logo_path": "/eWp5LdR4p4uKL0wACBBXapDV2lB.jpg",
            "provider_id": 43,
            "provider_name": "Starz",
            "display_priority": 44
          },
          {
            "logo_path": "/x36C6aseF5l4uX99Kpse9dbPwBo.jpg",
            "provider_id": 1794,
            "provider_name": "Starz Amazon Channel",
            "display_priority": 221
          }
        ],
        "buy": [
          {
            "logo_path": "/peURlLlr8jggOwK53fJ5wdQl05y.jpg",
            "provider_id": 2,
            "provider_name": "Apple TV",
            "display_priority": 5
          },
          {
            "logo_path": "/5NyLm42TmCqCMOZFvH4fcoSNKEW.jpg",
            "provider_id": 10,
            "provider_name": "Amazon Video",
            "display_priority": 15
          },
          {
            "logo_path": "/tbEdFQDwx5LEVr8WpSeXQSIirVq.jpg",
            "provider_id": 3,
            "provider_name": "Google Play Movies",
            "display_priority": 16
          },
          {
            "logo_path": "/oIkQkEkwfmcG7IGpRR1NB8frZZM.jpg",
            "provider_id": 192,
            "provider_name": "YouTube",
            "display_priority": 17
          },
          {
            "logo_path": "/21dEscfO8n1tL35k4DANixhffsR.jpg",
            "provider_id": 7,
            "provider_name": "Vudu",
            "display_priority": 42
          },
          {
            "logo_path": "/shq88b09gTBYC4hA7K7MUL8Q4zP.jpg",
            "provider_id": 68,
            "provider_name": "Microsoft Store",
            "display_priority": 53
          },
          {
            "logo_path": "/xL9SUR63qrEjFZAhtsipskeAMR7.jpg",
            "provider_id": 358,
            "provider_name": "DIRECTV",
            "display_priority": 58
          },
          {
            "logo_path": "/pPLjA4eW9186YXMh48r7pmLoNYH.jpg",
            "provider_id": 1957,
            "provider_name": "Cineverse",
            "display_priority": 257
          }
        ],
        "rent": [
          {
            "logo_path": "/peURlLlr8jggOwK53fJ5wdQl05y.jpg",
            "provider_id": 2,
            "provider_name": "Apple TV",
            "display_priority": 5
          },
          {
            "logo_path": "/5NyLm42TmCqCMOZFvH4fcoSNKEW.jpg",
            "provider_id": 10,
            "provider_name": "Amazon Video",
            "display_priority": 15
          },
          {
            "logo_path": "/tbEdFQDwx5LEVr8WpSeXQSIirVq.jpg",
            "provider_id": 3,
            "provider_name": "Google Play Movies",
            "display_priority": 16
          },
          {
            "logo_path": "/oIkQkEkwfmcG7IGpRR1NB8frZZM.jpg",
            "provider_id": 192,
            "provider_name": "YouTube",
            "display_priority": 17
          },
          {
            "logo_path": "/21dEscfO8n1tL35k4DANixhffsR.jpg",
            "provider_id": 7,
            "provider_name": "Vudu",
            "display_priority": 42
          },
          {
            "logo_path": "/shq88b09gTBYC4hA7K7MUL8Q4zP.jpg",
            "provider_id": 68,
            "provider_name": "Microsoft Store",
            "display_priority": 53
          },
          {
            "logo_path": "/xL9SUR63qrEjFZAhtsipskeAMR7.jpg",
            "provider_id": 358,
            "provider_name": "DIRECTV",
            "display_priority": 58
          },
          {
            "logo_path": "/4U02VrbgLfUKJAUCHKzxWFtnPx4.jpg",
            "provider_id": 331,
            "provider_name": "FlixFling",
            "display_priority": 133
          },
          {
            "logo_path": "/1tLCqSH5xiViDxMiTVWl6DmE8hd.jpg",
            "provider_id": 486,
            "provider_name": "Spectrum On Demand",
            "display_priority": 169
          },
          {
            "logo_path": "/pPLjA4eW9186YXMh48r7pmLoNYH.jpg",
            "provider_id": 1957,
            "provider_name": "Cineverse",
            "display_priority": 257
          }
        ]
      }
    }
  }